CHANGELOG.md
LICENSE
MANIFEST.in
Makefile
README.md
setup.cfg
setup.py
tox.ini
tests/test_registry.py
tests/test_request_resolver.py
wc_django_device_recognizer.egg-info/PKG-INFO
wc_django_device_recognizer.egg-info/SOURCES.txt
wc_django_device_recognizer.egg-info/dependency_links.txt
wc_django_device_recognizer.egg-info/requires.txt
wc_django_device_recognizer.egg-info/top_level.txt
wcd_device_recognizer/__init__.py
wcd_device_recognizer/admin.py
wcd_device_recognizer/apps.py
wcd_device_recognizer/conf.py
wcd_device_recognizer/const.py
wcd_device_recognizer/discovery.py
wcd_device_recognizer/dtos.py
wcd_device_recognizer/models.py
wcd_device_recognizer/utils.py
wcd_device_recognizer/locale/af/LC_MESSAGES/django.mo
wcd_device_recognizer/locale/af/LC_MESSAGES/django.po
wcd_device_recognizer/locale/ar/LC_MESSAGES/django.mo
wcd_device_recognizer/locale/ar/LC_MESSAGES/django.po
wcd_device_recognizer/locale/ast/LC_MESSAGES/django.mo
wcd_device_recognizer/locale/ast/LC_MESSAGES/django.po
wcd_device_recognizer/locale/az/LC_MESSAGES/django.mo
wcd_device_recognizer/locale/az/LC_MESSAGES/django.po
wcd_device_recognizer/locale/be/LC_MESSAGES/django.mo
wcd_device_recognizer/locale/be/LC_MESSAGES/django.po
wcd_device_recognizer/locale/bg/LC_MESSAGES/django.mo
wcd_device_recognizer/locale/bg/LC_MESSAGES/django.po
wcd_device_recognizer/locale/bn/LC_MESSAGES/django.mo
wcd_device_recognizer/locale/bn/LC_MESSAGES/django.po
wcd_device_recognizer/locale/br/LC_MESSAGES/django.mo
wcd_device_recognizer/locale/br/LC_MESSAGES/django.po
wcd_device_recognizer/locale/bs/LC_MESSAGES/django.mo
wcd_device_recognizer/locale/bs/LC_MESSAGES/django.po
wcd_device_recognizer/locale/ca/LC_MESSAGES/django.mo
wcd_device_recognizer/locale/ca/LC_MESSAGES/django.po
wcd_device_recognizer/locale/cs/LC_MESSAGES/django.mo
wcd_device_recognizer/locale/cs/LC_MESSAGES/django.po
wcd_device_recognizer/locale/cy/LC_MESSAGES/django.mo
wcd_device_recognizer/locale/cy/LC_MESSAGES/django.po
wcd_device_recognizer/locale/da/LC_MESSAGES/django.mo
wcd_device_recognizer/locale/da/LC_MESSAGES/django.po
wcd_device_recognizer/locale/de/LC_MESSAGES/django.mo
wcd_device_recognizer/locale/de/LC_MESSAGES/django.po
wcd_device_recognizer/locale/dsb/LC_MESSAGES/django.mo
